LICENSE.txt
MANIFEST.in
README.md
setup.cfg
setup.py
speview.py
version.py
speview.egg-info/PKG-INFO
speview.egg-info/SOURCES.txt
speview.egg-info/dependency_links.txt
speview.egg-info/requires.txt
speview.egg-info/top_level.txt
testdata/calibration-cyclohexane.SPE
testdata/calibration-dark.SPE
testdata/calibration-polystyrene.SPE
testdata/data-dark.SPE
testdata/data-sample_1-plastic.SPE
testdata/data-sample_2-polystyrene_plate.SPE
testdata/data-sample_3-paracetamol.SPE
testdata/data-sample_4-plastic.SPE
testdata/data-sample_5-paper.SPE