Metadata-Version: 1.0
Name: speview
Version: 0.5.1
Summary: Program to display binary SPE files containing Raman spectra
Home-page: https://github.com/ximeg/speview
Author: Roman Kiselev
Author-email: roman.kiselew@gmail.com
License: LICENSE.txt
Platform: UNKNOWN
